LICENSE
MANIFEST.in
README.md
scrapy.cfg
setup.cfg
setup.py
os_scrapy_uvicorn/__init__.py
os_scrapy_uvicorn/example.py
os_scrapy_uvicorn/extensions.py
os_scrapy_uvicorn/items.py
os_scrapy_uvicorn/middlewares.py
os_scrapy_uvicorn/pipelines.py
os_scrapy_uvicorn/settings.py
os_scrapy_uvicorn.egg-info/PKG-INFO
os_scrapy_uvicorn.egg-info/SOURCES.txt
os_scrapy_uvicorn.egg-info/dependency_links.txt
os_scrapy_uvicorn.egg-info/not-zip-safe
os_scrapy_uvicorn.egg-info/requires.txt
os_scrapy_uvicorn.egg-info/top_level.txt
os_scrapy_uvicorn/spiders/__init__.py
requirements/requirements-lint.txt
requirements/requirements-test.txt
requirements/requirements.txt
tests/__init__.py
tests/test_scrapy_check.py